pbn/__init__.py
pbn/paint_by_numbers.py
pbn-0.1.0.dist-info/METADATA
pbn-0.1.0.dist-info/WHEEL
pbn-0.1.0.dist-info/top_level.txt
pbn-0.1.0.dist-info/RECORD
